candiy_lemon-0.3.0.dist-info/RECORD
candiy_lemon-0.3.0.dist-info/METADATA
candiy_lemon-0.3.0.dist-info/WHEEL
candiy_lemon-0.3.0.dist-info/top_level.txt
candiy_lemon/lemon.cpython-35m-x86_64-linux-gnu.so
candiy_lemon/__init__.py
candiy_lemon-0.3.0.data/data/lib/cmake/lemon/lemon-config-version.cmake
candiy_lemon-0.3.0.data/data/lib/cmake/lemon/lemon-targets.cmake
candiy_lemon-0.3.0.data/data/lib/cmake/lemon/lemon-config.cmake
candiy_lemon-0.3.0.data/data/include/lemon/residue_name.hpp
candiy_lemon-0.3.0.data/data/include/lemon/entries.hpp
candiy_lemon-0.3.0.data/data/include/lemon/prune.hpp
candiy_lemon-0.3.0.data/data/include/lemon/parallel.hpp
candiy_lemon-0.3.0.data/data/include/lemon/select.hpp
candiy_lemon-0.3.0.data/data/include/lemon/thread_pool.hpp
candiy_lemon-0.3.0.data/data/include/lemon/count.hpp
candiy_lemon-0.3.0.data/data/include/lemon/matrix.hpp
candiy_lemon-0.3.0.data/data/include/lemon/tmalign.hpp
candiy_lemon-0.3.0.data/data/include/lemon/xscore.hpp
candiy_lemon-0.3.0.data/data/include/lemon/hadoop.hpp
candiy_lemon-0.3.0.data/data/include/lemon/lemon.hpp
candiy_lemon-0.3.0.data/data/include/lemon/geometry.hpp
candiy_lemon-0.3.0.data/data/include/lemon/launch.hpp
candiy_lemon-0.3.0.data/data/include/lemon/constants.hpp
candiy_lemon-0.3.0.data/data/include/lemon/separate.hpp
candiy_lemon-0.3.0.data/data/include/lemon/options.hpp
candiy_lemon-0.3.0.data/data/include/lemon/deprecated/old_hadoop.hpp
candiy_lemon-0.3.0.data/data/include/lemon/external/gaurd.hpp
candiy_lemon-0.3.0.data/data/include/lemon/external/CLI11.hpp
candiy_lemon-0.3.0.data/data/include/lemon/external/dirent.hpp
